dm2gym/__init__.py
dm2gym/envs/__init__.py
dm2gym/envs/dm_suite_env.py
dm2gym/envs/opencv_image_viewer.py
dm2gym-0.2.0.dist-info/LICENSE
dm2gym-0.2.0.dist-info/METADATA
dm2gym-0.2.0.dist-info/WHEEL
dm2gym-0.2.0.dist-info/top_level.txt
dm2gym-0.2.0.dist-info/RECORD
