Metadata-Version: 2.1
Name: dm2gym
Version: 0.2.0
Summary: dm2gym: Convert DeepMind Control Suite to OpenAI gym environments.
Home-page: https://github.com/zuoxingdong/dm2gym
Author: Xingdong Zuo
Author-email: zuoxingdong@hotmail.com
License: UNKNOWN
Platform: UNKNOWN
Classifier: Programming Language :: Python :: 3
Classifier: License :: OSI Approved :: MIT License
Classifier: Operating System :: OS Independent
Classifier: Natural Language :: English
Classifier: Topic :: Scientific/Engineering :: Artificial Intelligence
Requires-Python: >=3
Requires-Dist: numpy
Requires-Dist: gym
